Locales/__init__.py
Locales-0.0.2.dist-info/LICENSE
Locales-0.0.2.dist-info/METADATA
Locales-0.0.2.dist-info/WHEEL
Locales-0.0.2.dist-info/top_level.txt
Locales-0.0.2.dist-info/RECORD
