Metadata-Version: 2.1
Name: Locales
Version: 0.0.2
Summary: Module for multilingual solutions
Home-page: https://github.com/vffuunnyy/Locales
Author: vffuunnyy
Author-email: vffuunnyy@gmail.com
License: UNKNOWN
Platform: UNKNOWN
Classifier: Programming Language :: Python :: 3
Classifier: License :: OSI Approved :: MIT License
Classifier: Operating System :: OS Independent
